lsst_efd_client/__init__.py
lsst_efd_client/auth_helper.py
lsst_efd_client/efd_helper.py
lsst_efd_client/efd_utils.py
lsst_efd_client-0.13.1.dist-info/AUTHORS.rst
lsst_efd_client-0.13.1.dist-info/LICENSE
lsst_efd_client-0.13.1.dist-info/METADATA
lsst_efd_client-0.13.1.dist-info/WHEEL
lsst_efd_client-0.13.1.dist-info/top_level.txt
lsst_efd_client-0.13.1.dist-info/RECORD
