Metadata-Version: 2.1
Name: lsst-efd-client
Version: 0.13.1
Summary: Utility classes for working with the LSST EFD.
Home-page: https://github.com/lsst-sqre/lsst-efd-client
Author: Simon Krughoff
Author-email: krughoff@lsst.org
License: MIT license
Keywords: LSST,EFD
Classifier: Development Status :: 2 - Pre-Alpha
Classifier: Intended Audience :: Developers
Classifier: License :: OSI Approved :: MIT License
Classifier: Natural Language :: English
Classifier: Programming Language :: Python :: 3
Classifier: Programming Language :: Python :: 3.5
Classifier: Programming Language :: Python :: 3.6
Classifier: Programming Language :: Python :: 3.7
Classifier: Programming Language :: Python :: 3.8
Requires-Python: >=3.5
License-File: LICENSE
License-File: AUTHORS.rst
Requires-Dist: numpy (==1.23.5)
Requires-Dist: aioinflux
Requires-Dist: pandas
Requires-Dist: astropy
Requires-Dist: pyyaml
Requires-Dist: tables
Requires-Dist: kafkit
Provides-Extra: dev
Requires-Dist: documenteer[pipelines] ; extra == 'dev'
Requires-Dist: docutils (<0.18) ; extra == 'dev'
